
[
    {
        "Word": "dzo",
        "definition": "a hybrid between the yak and the domestic cow"
    },
    {
        "Word": "dysbulla",
        "definition": "loss of will power"
    },
    {
        "Word": "calamistrate",
        "definition": "to curl, crisp, frizzle the hair"
    },
    {
        "Word": "essomenic",
        "definition": "a mirror that shows things as they will be in the future"
    },
    {
        "Word": "Famelicose",
        "definition": "often or very hungry"
    },
    {
        "Word": "Gardeviance",
        "definition": "chest for valuables; a traveling trunk"
    },
    {
        "Word": "Honily",
        "definition": "like honey; as of honey"
    },
    {
        "Word": "Ingordigious",
        "definition": "greedy, avaricious"
    },
    {
        "Word": "Juise",
        "definition": "judgement, doom"
    },
    {
        "Word": "Kebber",
        "definition": "a crone"
    },
    {
        "Word": "Launchant",
        "definition": "darting, leaping"
    },
    {
        "Word": "Murklins",
        "definition": "in the dark"
    },
    {
        "Word": "Nerterology",
        "definition": "learning relating to the dead or the underworld"
    },
    {
        "Word": "Obtortion",
        "definition": " the practice of obtaining something"
    },
    {
        "Word": "Queme",
        "definition": "to please, gratify"
    },
    {
        "Word": "Redamancy",
        "definition": "the act of loving in return"
    },
    {
        "Word": "Ughten",
        "definition": "the part of night immediately before daybreak"
    },
    {
        "Word": "Xenodochial",
        "definition": "given to receiving strangers; hospitable"
    },
    {
        "Word": "Yemelich",
        "definition": "full of care, anxious "
    },
    {
        "Word": "Enceinte",
        "definition": "the main enclosure of a fortress "
    },
    {
        "Word": "Esquamate",
        "definition": "having no scales"
    },
    {
        "Word": "estuous",
        "definition": "excited, passionate"
    },
    {
        "Word": "Xeric",
        "definition": "having very little moisture"
    },
    {
        "Word": "Ineffable",
        "definition": "Too great or extreme to be expressed or described in words."
    },
    {
        "Word": "Sesquipedalian",
        "definition": "(Of a word) long and difficult; characterized by long words."
    },
    {
        "Word": "Obfuscate",
        "definition": "To deliberately make something unclear or difficult to understand."
    },
    {
        "Word": "Perspicacious",
        "definition": "Having a ready insight into and understanding of things; keen-minded."
    },
    {
        "Word": "Anachronism",
        "definition": "Something or someone that is out of place in time; something that belongs to an earlier time period."
    },
    {
        "Word": "Surreptitious",
        "definition": "Kept secret, especially because it would not be approved of."
    },
    {
        "Word": "Panacea",
        "definition": "A universal remedy for all diseases or problems."
    },
    {
        "Word": "Cacophony",
        "definition": "A harsh, discordant mixture of sounds."
    },
    {
        "Word": "Apotheosis",
        "definition": "The highest point in the development of something; a culmination or climax."
    },
    {
        "Word": "Sagacious",
        "definition": "Having or showing keen mental discernment and good judgment."
    },
    {
        "Word": "Obsequious",
        "definition": "Obedient or attentive to an excessive or servile degree."
    },
    {
        "Word": "Vicissitude",
        "definition": "A change of circumstances or fortune, typically one that is unwelcome or unpleasant."
    },
    {
        "Word": "Excoriate",
        "definition": "To criticize severely and publicly."
    },
    {
        "Word": "Perspicuity",
        "definition": "Clearness or lucidity, as of a statement."
    },
    {
        "Word": "Ephemeral",
        "definition": "Lasting for a very short time; fleeting."
    },
    {
        "Word": "Ubiquitous",
        "definition": "Present, appearing, or found everywhere."
    },
    {
        "Word": "Pusillanimous",
        "definition": "Lacking courage or resolution; cowardly."
    },
    {
        "Word": "Obdurate",
        "definition": "Stubbornly refusing to change one's opinion or course of action."
    },
    {
        "Word": "Vicissitudinary",
        "definition": "Relating to or characterized by change or variation, especially in fortune."
    },
    {
        "Word": "Soliloquy",
        "definition": "An act of speaking one's thoughts aloud when by oneself or regardless of any hearers."
    }
]
